{
  "records": [
    {
      "recordId": "d519151d-67a5-4500-8f7b-037bf299e33a",
      "instanceId": "i-09dea164a6f2c9d5f",
      "date": "2022-11-30T07:19:00",
      "type": 0
    },
    {
      "recordId": "382ffbd6-d9a6-4588-8934-62ce53e367c1",
      "instanceId": "i-09dea164a6f2c9d5f",
      "date": "2022-11-30T07:20:00",
      "type": 0
    },
    {
      "recordId": "7fcb801f-3722-41a9-8114-5f7725ec7034",
      "instanceId": "i-09dea164a6f2c9d5f",
      "date": "2022-11-30T07:21:00",
      "type": 0
    },
    {
      "recordId": "7190b563-0757-4139-a847-4e1957fff363",
      "instanceId": "i-09dea164a6f2c9d5f",
      "date": "2022-11-30T07:22:00",
      "type": 0
    },
    {
      "recordId": "894f427a-c8d1-48f1-85ba-f61511548530",
      "instanceId": "i-09dea164a6f2c9d5f",
      "date": "2022-11-30T07:23:00",
      "type": 0
    },
    {
      "recordId": "d946d49c-bf0f-4fd8-ae7e-ca76ae4ae73e",
      "instanceId": "i-09dea164a6f2c9d5f",
      "date": "2022-11-30T07:24:00",
      "type": 0
    },
    {
      "recordId": "4b7de3e9-b815-4b91-b4f0-4e0d54201c37",
      "instanceId": "i-09dea164a6f2c9d5f",
      "date": "2022-11-30T07:25:00",
      "type": 0
    },
    {
      "recordId": "c4fc01a8-782d-48a7-a937-5a7995886e9d",
      "instanceId": "i-09dea164a6f2c9d5f",
      "date": "2022-11-30T07:28:00",
      "type": 0
    },
    {
      "recordId": "efaadea4-aba2-491b-9e38-4dcaab615cd8",
      "instanceId": "i-09dea164a6f2c9d5f",
      "date": "2022-11-30T07:29:00",
      "type": 0
    },
    {
      "recordId": "7e756595-c0e3-46dc-9df1-0d57c009b7c7",
      "instanceId": "i-09dea164a6f2c9d5f",
      "date": "2022-11-30T07:30:00",
      "type": 0
    },
    {
      "recordId": "50a7146a-b476-43dc-92b5-54b19fe04d56",
      "instanceId": "i-09dea164a6f2c9d5f",
      "date": "2022-11-30T07:31:00",
      "type": 0
    },
    {
      "recordId": "aea30b39-145b-4683-b189-1a2f8d566b74",
      "instanceId": "i-09dea164a6f2c9d5f",
      "date": "2022-11-30T07:32:00",
      "type": 0
    },
    {
      "recordId": "136ec644-0809-45c4-8a61-0534c8248c50",
      "instanceId": "i-09dea164a6f2c9d5f",
      "date": "2022-11-30T07:33:00",
      "type": 0
    },
    {
      "recordId": "06579bf7-afdb-4540-9ede-771be5cdc352",
      "instanceId": "i-09dea164a6f2c9d5f",
      "date": "2022-11-30T07:34:00",
      "type": 0
    },
    {
      "recordId": "26e0ea70-a718-4abc-81ff-295d796a5405",
      "instanceId": "i-09dea164a6f2c9d5f",
      "date": "2022-11-30T07:35:00",
      "type": 0
    },
    {
      "recordId": "d89c93f6-9a63-4d3a-be8c-e94425d6248b",
      "instanceId": "i-09dea164a6f2c9d5f",
      "date": "2022-11-30T07:36:00",
      "type": 0
    },
    {
      "recordId": "e3008656-9b53-48a3-8fa8-822c407ead42",
      "instanceId": "i-09dea164a6f2c9d5f",
      "date": "2022-11-30T07:37:00",
      "type": 0
    },
    {
      "recordId": "cd582a9d-333c-41af-b3ea-5a7e90f30668",
      "instanceId": "i-09dea164a6f2c9d5f",
      "date": "2022-11-30T07:38:00",
      "type": 0
    },
    {
      "recordId": "4ed807e9-ac80-4a97-a345-41cd4579c31c",
      "instanceId": "i-09dea164a6f2c9d5f",
      "date": "2022-11-30T07:39:00",
      "type": 0
    },
    {
      "recordId": "4c1de3fd-fe34-446e-9595-e51150c7601b",
      "instanceId": "i-09dea164a6f2c9d5f",
      "date": "2022-11-30T07:40:00",
      "type": 0
    },
    {
      "recordId": "1d5e79c0-12ec-42c6-bff2-09da69ead143",
      "instanceId": "i-09dea164a6f2c9d5f",
      "date": "2022-11-30T07:41:00",
      "type": 0
    },
    {
      "recordId": "abc7c839-2568-4e7f-aef9-0234b708fdb2",
      "instanceId": "i-09dea164a6f2c9d5f",
      "date": "2022-11-30T07:42:00",
      "type": 0
    },
    {
      "recordId": "65dcc1e5-c037-47d4-845c-090acb5001d6",
      "instanceId": "i-09dea164a6f2c9d5f",
      "date": "2022-11-30T07:43:00",
      "type": 0
    },
    {
      "recordId": "56266e0b-be10-435e-b5aa-e25347001900",
      "instanceId": "i-09dea164a6f2c9d5f",
      "date": "2022-11-30T07:44:00",
      "type": 0
    },
    {
      "recordId": "eea48512-cbb4-4f6a-872f-0085a991ec11",
      "instanceId": "i-09dea164a6f2c9d5f",
      "date": "2022-11-30T07:45:00",
      "type": 0
    },
    {
      "recordId": "6ec41332-d034-47a1-b50d-d07ed0439eeb",
      "instanceId": "i-09dea164a6f2c9d5f",
      "date": "2022-11-30T07:46:00",
      "type": 0
    },
    {
      "recordId": "44961fec-f4b8-454a-9367-c775cfc80c34",
      "instanceId": "i-09dea164a6f2c9d5f",
      "date": "2022-11-30T07:47:00",
      "type": 0
    },
    {
      "recordId": "328cb0e0-4662-4cd1-977f-b9e06286b7f3",
      "instanceId": "i-09dea164a6f2c9d5f",
      "date": "2022-11-30T07:48:00",
      "type": 0
    },
    {
      "recordId": "47d6618d-9e65-4288-9298-b3f672c8ff80",
      "instanceId": "i-09dea164a6f2c9d5f",
      "date": "2022-11-30T07:49:00",
      "type": 0
    },
    {
      "recordId": "07f00101-e956-4e10-8691-2a539a30c2f8",
      "instanceId": "i-09dea164a6f2c9d5f",
      "date": "2022-11-30T07:50:00",
      "type": 0
    },
    {
      "recordId": "ace88ebc-f3a4-46ae-a6e4-e594e117ca80",
      "instanceId": "i-09dea164a6f2c9d5f",
      "date": "2022-11-30T07:51:00",
      "type": 0
    },
    {
      "recordId": "f9a29a13-b3de-49aa-992b-96ab6f43cca2",
      "instanceId": "i-09dea164a6f2c9d5f",
      "date": "2022-11-30T07:52:00",
      "type": 0
    },
    {
      "recordId": "d904ac9b-7d68-4a22-92b0-c8dd1c035d1e",
      "instanceId": "i-09dea164a6f2c9d5f",
      "date": "2022-11-30T07:53:00",
      "type": 0
    },
    {
      "recordId": "31dc9c86-68f3-4519-8b6f-d5ef8c5c1673",
      "instanceId": "i-09dea164a6f2c9d5f",
      "date": "2022-11-30T07:54:00",
      "type": 0
    },
    {
      "recordId": "31ffcaec-0deb-4ef4-a370-a956a1a7104a",
      "instanceId": "i-09dea164a6f2c9d5f",
      "date": "2022-11-30T07:55:00",
      "type": 0
    },
    {
      "recordId": "91345f44-9c37-4b2c-9f8a-aa2e10902f09",
      "instanceId": "i-09dea164a6f2c9d5f",
      "date": "2022-11-30T07:56:00",
      "type": 0
    },
    {
      "recordId": "83d18ff1-2541-46d4-b55d-e0be1099badd",
      "instanceId": "i-09dea164a6f2c9d5f",
      "date": "2022-11-30T07:57:00",
      "type": 0
    },
    {
      "recordId": "469e6965-4559-457a-8395-a12f5bfb1595",
      "instanceId": "i-09dea164a6f2c9d5f",
      "date": "2022-11-30T07:58:00",
      "type": 0
    },
    {
      "recordId": "feef4cd4-e1cd-493f-8e70-d6ec60ad22bd",
      "instanceId": "i-09dea164a6f2c9d5f",
      "date": "2022-11-30T07:59:00",
      "type": 0
    },
    {
      "recordId": "0ab276a5-220c-4571-8750-6f6460d01811",
      "instanceId": "i-09dea164a6f2c9d5f",
      "date": "2022-11-30T08:00:00",
      "type": 0
    },
    {
      "recordId": "c7459652-810c-47b1-be4a-2d7d4b1d4ae6",
      "instanceId": "i-09dea164a6f2c9d5f",
      "date": "2022-11-30T08:01:00",
      "type": 0
    },
    {
      "recordId": "a58e9e62-2a11-4f46-8f38-0d595701010f",
      "instanceId": "i-09dea164a6f2c9d5f",
      "date": "2022-11-30T08:02:00",
      "type": 0
    },
    {
      "recordId": "f08f1b75-bb8f-4ca4-9ddb-4cb2e95d0755",
      "instanceId": "i-09dea164a6f2c9d5f",
      "date": "2022-11-30T08:03:00",
      "type": 0
    },
    {
      "recordId": "116cab44-1cd2-413b-ac19-e4d4cc49b7f7",
      "instanceId": "i-09dea164a6f2c9d5f",
      "date": "2022-11-30T08:04:00",
      "type": 0
    },
    {
      "recordId": "fc310809-8954-468d-be3c-c6f6461821d9",
      "instanceId": "i-09dea164a6f2c9d5f",
      "date": "2022-11-30T08:05:00",
      "type": 0
    },
    {
      "recordId": "4300ad00-d45f-45be-b993-6f006d8f2917",
      "instanceId": "i-09dea164a6f2c9d5f",
      "date": "2022-11-30T08:06:00",
      "type": 0
    },
    {
      "recordId": "c6ff3454-b6af-4b7e-8469-0e10da2f0f28",
      "instanceId": "i-09dea164a6f2c9d5f",
      "date": "2022-11-30T08:07:00",
      "type": 0
    },
    {
      "recordId": "d5b9faf5-37c5-4f61-909b-64a5961e94f3",
      "instanceId": "i-09dea164a6f2c9d5f",
      "date": "2022-11-30T08:08:00",
      "type": 0
    },
    {
      "recordId": "32de4d9e-cb47-4995-9d8d-68bf1ba5fd40",
      "instanceId": "i-09dea164a6f2c9d5f",
      "date": "2022-11-30T08:09:00",
      "type": 0
    },
    {
      "recordId": "b96e302b-298f-4889-bd47-e56795b5086f",
      "instanceId": "i-09dea164a6f2c9d5f",
      "date": "2022-11-30T08:10:00",
      "type": 0
    },
    {
      "recordId": "4733f850-56da-4bdb-ab70-93cb425e8dec",
      "instanceId": "i-09dea164a6f2c9d5f",
      "date": "2022-11-30T08:11:00",
      "type": 0
    },
    {
      "recordId": "f27462fd-fb66-41ae-bfed-9ba771ecae62",
      "instanceId": "i-09dea164a6f2c9d5f",
      "date": "2022-11-30T08:12:00",
      "type": 0
    },
    {
      "recordId": "2724f01d-5d82-457e-b6c8-44dcc8047f8b",
      "instanceId": "i-09dea164a6f2c9d5f",
      "date": "2022-11-30T08:13:00",
      "type": 0
    },
    {
      "recordId": "4301e8ce-1d81-473a-b578-6800ff9bf5a5",
      "instanceId": "i-09dea164a6f2c9d5f",
      "date": "2022-11-30T08:14:00",
      "type": 0
    },
    {
      "recordId": "de89d368-bb2e-45ed-8ac4-a07f845c3e9c",
      "instanceId": "i-09dea164a6f2c9d5f",
      "date": "2022-11-30T08:15:00",
      "type": 0
    },
    {
      "recordId": "4bb7c6db-7a5e-4397-84f7-4f410fa5bdec",
      "instanceId": "i-09dea164a6f2c9d5f",
      "date": "2022-11-30T08:16:00",
      "type": 0
    },
    {
      "recordId": "c6e69ba3-2519-4ee7-906e-548089a77849",
      "instanceId": "i-09dea164a6f2c9d5f",
      "date": "2022-11-30T08:17:00",
      "type": 0
    },
    {
      "recordId": "1a65723c-5690-4b19-8747-a1819cf589d6",
      "instanceId": "i-09dea164a6f2c9d5f",
      "date": "2022-11-30T08:18:00",
      "type": 0
    },
    {
      "recordId": "eef59dde-29cd-4361-b8b2-c6deffd0adf0",
      "instanceId": "i-09dea164a6f2c9d5f",
      "date": "2022-11-30T08:19:00",
      "type": 0
    },
    {
      "recordId": "004d354b-85f7-4b68-93f8-f071323ace22",
      "instanceId": "i-09dea164a6f2c9d5f",
      "date": "2022-11-30T08:20:00",
      "type": 0
    },
    {
      "recordId": "39e62905-3ddc-4eb6-a72a-3377fc63f261",
      "instanceId": "i-09dea164a6f2c9d5f",
      "date": "2022-11-30T08:21:00",
      "type": 0
    },
    {
      "recordId": "9792dca1-0d9e-4f23-b43a-e71f346f7099",
      "instanceId": "i-09dea164a6f2c9d5f",
      "date": "2022-11-30T08:22:00",
      "type": 0
    },
    {
      "recordId": "ff26d7c7-46ab-4803-a214-4bb960689438",
      "instanceId": "i-09dea164a6f2c9d5f",
      "date": "2022-11-30T08:23:00",
      "type": 0
    },
    {
      "recordId": "07ca0dcb-fc2e-4281-a9fa-3cb8814a21be",
      "instanceId": "i-09dea164a6f2c9d5f",
      "date": "2022-11-30T08:24:00",
      "type": 0
    },
    {
      "recordId": "8fbb6af6-fd4d-414d-8f47-81d4c41b1b65",
      "instanceId": "i-09dea164a6f2c9d5f",
      "date": "2022-11-30T08:25:00",
      "type": 0
    },
    {
      "recordId": "7fa84842-d3f2-49d4-becd-06074db789d8",
      "instanceId": "i-09dea164a6f2c9d5f",
      "date": "2022-11-30T08:26:00",
      "type": 0
    },
    {
      "recordId": "174ff3dd-4ef6-4fb2-bda4-bf7b3addb2a4",
      "instanceId": "i-09dea164a6f2c9d5f",
      "date": "2022-11-30T08:27:00",
      "type": 0
    },
    {
      "recordId": "96818b04-eedc-4b9d-9114-480c65a6b679",
      "instanceId": "i-09dea164a6f2c9d5f",
      "date": "2022-11-30T08:28:00",
      "type": 0
    },
    {
      "recordId": "a9e4b388-c751-4028-80f6-788b4e016378",
      "instanceId": "i-09dea164a6f2c9d5f",
      "date": "2022-11-30T08:29:00",
      "type": 0
    },
    {
      "recordId": "51eaef2c-087b-42cc-951b-57b8ca935f8b",
      "instanceId": "i-09dea164a6f2c9d5f",
      "date": "2022-11-30T08:30:00",
      "type": 0
    },
    {
      "recordId": "9faf0b8f-cb73-413b-921a-4abbaa492faf",
      "instanceId": "i-09dea164a6f2c9d5f",
      "date": "2022-11-30T08:31:00",
      "type": 0
    },
    {
      "recordId": "c9fa2ba6-6c91-447e-aba3-087e2062b299",
      "instanceId": "i-09dea164a6f2c9d5f",
      "date": "2022-11-30T08:32:00",
      "type": 0
    },
    {
      "recordId": "19a040c3-cc73-42d1-9071-172b6328484b",
      "instanceId": "i-09dea164a6f2c9d5f",
      "date": "2022-11-30T08:33:00",
      "type": 0
    },
    {
      "recordId": "ca084040-ca81-4711-b3dc-d60835a52481",
      "instanceId": "i-09dea164a6f2c9d5f",
      "date": "2022-11-30T08:34:00",
      "type": 0
    },
    {
      "recordId": "d2e017ac-0ef1-4823-862b-b1afddc3ec01",
      "instanceId": "i-09dea164a6f2c9d5f",
      "date": "2022-11-30T08:35:00",
      "type": 0
    },
    {
      "recordId": "6ac13064-3b5c-44ea-a696-49bb459df477",
      "instanceId": "i-09dea164a6f2c9d5f",
      "date": "2022-11-30T08:36:00",
      "type": 0
    },
    {
      "recordId": "7dd18080-4d6f-4325-85fb-9e4ccc76f29d",
      "instanceId": "i-09dea164a6f2c9d5f",
      "date": "2022-11-30T08:37:00",
      "type": 0
    },
    {
      "recordId": "853ce2d4-41ef-4f4a-af62-4b1a437c9e15",
      "instanceId": "i-09dea164a6f2c9d5f",
      "date": "2022-11-30T08:38:00",
      "type": 0
    },
    {
      "recordId": "126cb3c0-bb89-4fc1-a9fb-585c26ce8990",
      "instanceId": "i-09dea164a6f2c9d5f",
      "date": "2022-11-30T08:39:00",
      "type": 0
    },
    {
      "recordId": "845ffb74-9ce6-4ce9-821e-a03b1eb1d7a4",
      "instanceId": "i-09dea164a6f2c9d5f",
      "date": "2022-11-30T08:40:00",
      "type": 0
    },
    {
      "recordId": "7f581abe-a99e-4d32-851e-87ab4a808a9d",
      "instanceId": "i-09dea164a6f2c9d5f",
      "date": "2022-11-30T08:41:00",
      "type": 0
    },
    {
      "recordId": "20bbaf72-3375-444e-8c1c-110587e23444",
      "instanceId": "i-09dea164a6f2c9d5f",
      "date": "2022-11-30T08:42:00",
      "type": 0
    },
    {
      "recordId": "13e617dc-9a95-4754-80d8-e88b51be9300",
      "instanceId": "i-09dea164a6f2c9d5f",
      "date": "2022-11-30T08:43:00",
      "type": 0
    },
    {
      "recordId": "ef9d3747-ee7f-437d-8f0f-7840fcce0ca2",
      "instanceId": "i-09dea164a6f2c9d5f",
      "date": "2022-11-30T08:44:00",
      "type": 0
    },
    {
      "recordId": "8af8512c-d8ff-4897-9265-b6f6bc704525",
      "instanceId": "i-09dea164a6f2c9d5f",
      "date": "2022-11-30T08:45:00",
      "type": 0
    },
    {
      "recordId": "99f93919-fb60-4c63-83e6-7cb4460d4054",
      "instanceId": "i-09dea164a6f2c9d5f",
      "date": "2022-11-30T08:46:00",
      "type": 0
    },
    {
      "recordId": "7c1b841f-b25d-47ea-a89b-baec56611145",
      "instanceId": "i-09dea164a6f2c9d5f",
      "date": "2022-11-30T08:47:00",
      "type": 0
    },
    {
      "recordId": "31352f2f-11df-4b68-a60e-1fa19130a728",
      "instanceId": "i-09dea164a6f2c9d5f",
      "date": "2022-11-30T08:48:00",
      "type": 0
    },
    {
      "recordId": "0fc83b50-d0a9-4cc1-8d26-902ea4e3d057",
      "instanceId": "i-09dea164a6f2c9d5f",
      "date": "2022-11-30T08:49:00",
      "type": 0
    },
    {
      "recordId": "ce808768-2245-41da-9cfb-a325702d1578",
      "instanceId": "i-09dea164a6f2c9d5f",
      "date": "2022-11-30T08:50:00",
      "type": 0
    },
    {
      "recordId": "33d47947-79d1-40d6-ba0f-43223d4b77e7",
      "instanceId": "i-09dea164a6f2c9d5f",
      "date": "2022-11-30T08:51:00",
      "type": 0
    },
    {
      "recordId": "46a367f6-9ac9-41e5-a193-72c1052752e0",
      "instanceId": "i-09dea164a6f2c9d5f",
      "date": "2022-11-30T08:52:00",
      "type": 0
    },
    {
      "recordId": "3a091db4-a577-4a9e-94c0-ce30b7019b7e",
      "instanceId": "i-09dea164a6f2c9d5f",
      "date": "2022-11-30T08:53:00",
      "type": 0
    },
    {
      "recordId": "4f023431-fd0f-4467-9f92-f3ca2ff1e030",
      "instanceId": "i-09dea164a6f2c9d5f",
      "date": "2022-11-30T08:54:00",
      "type": 0
    },
    {
      "recordId": "039eae80-127b-46d2-8889-7f042bce4448",
      "instanceId": "i-09dea164a6f2c9d5f",
      "date": "2022-11-30T08:55:00",
      "type": 0
    },
    {
      "recordId": "6a513cbf-ee26-4267-961a-6145882f960d",
      "instanceId": "i-09dea164a6f2c9d5f",
      "date": "2022-11-30T08:56:00",
      "type": 0
    },
    {
      "recordId": "f2c05bfe-0b78-43fe-a0d0-6adf38144ce0",
      "instanceId": "i-09dea164a6f2c9d5f",
      "date": "2022-11-30T08:57:00",
      "type": 0
    },
    {
      "recordId": "c155aed8-cbab-412b-bc9e-35f678dfdc1a",
      "instanceId": "i-09dea164a6f2c9d5f",
      "date": "2022-11-30T08:58:00",
      "type": 0
    },
    {
      "recordId": "c29e9e76-eb38-46eb-895b-612ba3e19a6d",
      "instanceId": "i-09dea164a6f2c9d5f",
      "date": "2022-11-30T17:33:00",
      "type": 0
    },
    {
      "recordId": "2118ad36-72bf-487e-8fbb-13c841d70bf3",
      "instanceId": "i-09dea164a6f2c9d5f",
      "date": "2022-11-30T17:34:00",
      "type": 0
    },
    {
      "recordId": "a7009fc2-0445-4df5-9ab4-0a687bc5a03a",
      "instanceId": "i-09dea164a6f2c9d5f",
      "date": "2022-11-30T17:35:00",
      "type": 0
    },
    {
      "recordId": "9e20cd93-f434-46df-9e4a-d3e0ff938260",
      "instanceId": "i-09dea164a6f2c9d5f",
      "date": "2022-11-30T17:36:00",
      "type": 0
    },
    {
      "recordId": "7b170357-34b7-49b9-bda7-d543ca5a4e80",
      "instanceId": "i-09dea164a6f2c9d5f",
      "date": "2022-11-30T17:37:00",
      "type": 0
    },
    {
      "recordId": "ca194aa2-1c84-42a9-b5fc-8e13ef4ccf5f",
      "instanceId": "i-09dea164a6f2c9d5f",
      "date": "2022-11-30T17:38:00",
      "type": 0
    },
    {
      "recordId": "44508f0d-18d0-40d8-826f-94ad2c379810",
      "instanceId": "i-09dea164a6f2c9d5f",
      "date": "2022-11-30T17:39:00",
      "type": 0
    },
    {
      "recordId": "838bc320-ac55-496c-817a-2d7355047282",
      "instanceId": "i-09dea164a6f2c9d5f",
      "date": "2022-11-30T17:40:00",
      "type": 0
    },
    {
      "recordId": "c7e6110b-79b1-4500-95bc-14fc6ad36878",
      "instanceId": "i-09dea164a6f2c9d5f",
      "date": "2022-11-30T17:41:00",
      "type": 0
    },
    {
      "recordId": "a8f8dd5a-c626-4ea4-88bf-66af5cddf068",
      "instanceId": "i-09dea164a6f2c9d5f",
      "date": "2022-11-30T17:42:00",
      "type": 0
    },
    {
      "recordId": "48549e3c-295e-4cbf-9b8d-6431c9aabacc",
      "instanceId": "i-09dea164a6f2c9d5f",
      "date": "2022-11-30T17:43:00",
      "type": 0
    },
    {
      "recordId": "c60b4208-1a57-424a-a245-7c7a462fc4b0",
      "instanceId": "i-09dea164a6f2c9d5f",
      "date": "2022-11-30T17:44:00",
      "type": 0
    },
    {
      "recordId": "f320a2bb-c537-4b4e-949e-549927539d73",
      "instanceId": "i-00780850d79c19900",
      "date": "2022-11-30T17:45:00",
      "type": 0
    },
    {
      "recordId": "f1e4a729-58db-47b2-8e7a-615e44893c4a",
      "instanceId": "i-09dea164a6f2c9d5f",
      "date": "2022-11-30T17:46:00",
      "type": 0
    },
    {
      "recordId": "1c06881e-5ed6-4751-b705-ddefabf0859d",
      "instanceId": "i-09dea164a6f2c9d5f",
      "date": "2022-11-30T17:47:00",
      "type": 0
    },
    {
      "recordId": "8bd0acb0-9e8b-4dcc-ad00-e1361869ac30",
      "instanceId": "i-09dea164a6f2c9d5f",
      "date": "2022-11-30T17:48:00",
      "type": 0
    },
    {
      "recordId": "daddeee9-8521-470f-8985-0eca214b834f",
      "instanceId": "i-09dea164a6f2c9d5f",
      "date": "2022-11-30T17:57:00",
      "type": 0
    },
    {
      "recordId": "ff1582e4-07bd-4641-922f-032d72b053fb",
      "instanceId": "i-09dea164a6f2c9d5f",
      "date": "2022-11-30T17:58:00",
      "type": 0
    },
    {
      "recordId": "8fc65683-44c4-4486-bf26-e795f0a9ae12",
      "instanceId": "i-09dea164a6f2c9d5f",
      "date": "2022-11-30T17:59:00",
      "type": 0
    },
    {
      "recordId": "0408b2fe-839a-4944-a1e0-963da0f95298",
      "instanceId": "i-09dea164a6f2c9d5f",
      "date": "2022-11-30T18:00:00",
      "type": 0
    },
    {
      "recordId": "42425acf-791d-4a77-b08d-e50357892ab5",
      "instanceId": "i-09dea164a6f2c9d5f",
      "date": "2022-11-30T18:01:00",
      "type": 0
    },
    {
      "recordId": "4ade89a4-96d7-4b39-bc62-a0ead16504df",
      "instanceId": "i-09dea164a6f2c9d5f",
      "date": "2022-11-30T18:02:00",
      "type": 0
    },
    {
      "recordId": "40ea46df-d2d4-4430-bb3e-e2993abf9dd9",
      "instanceId": "i-09dea164a6f2c9d5f",
      "date": "2022-11-30T18:03:00",
      "type": 0
    },
    {
      "recordId": "b490a3ee-b0e0-4355-b691-2ce5e85615a5",
      "instanceId": "i-09dea164a6f2c9d5f",
      "date": "2022-11-30T18:04:00",
      "type": 0
    },
    {
      "recordId": "9f44172e-0f3c-418c-8c62-f3c61c187995",
      "instanceId": "i-09dea164a6f2c9d5f",
      "date": "2022-11-30T18:05:00",
      "type": 0
    },
    {
      "recordId": "4bd21e18-ad88-428e-8c7f-7fa4e572ec1d",
      "instanceId": "i-09dea164a6f2c9d5f",
      "date": "2022-11-30T18:06:00",
      "type": 0
    },
    {
      "recordId": "8c25e8f4-e624-45e2-bdd5-6d043f177bed",
      "instanceId": "i-09dea164a6f2c9d5f",
      "date": "2022-11-30T18:07:00",
      "type": 0
    },
    {
      "recordId": "e78b708e-62b2-4c99-b577-1cd9359a1413",
      "instanceId": "i-09dea164a6f2c9d5f",
      "date": "2022-11-30T18:08:00",
      "type": 0
    },
    {
      "recordId": "bfbe1766-409a-4e0d-8985-2d5ffc091773",
      "instanceId": "i-09dea164a6f2c9d5f",
      "date": "2022-11-30T18:09:00",
      "type": 0
    },
    {
      "recordId": "be082c74-da9f-40b6-80b9-9303ab3d4ab2",
      "instanceId": "i-09dea164a6f2c9d5f",
      "date": "2022-11-30T18:10:00",
      "type": 0
    },
    {
      "recordId": "16d5da69-46ff-4bc7-babd-7f54470cf6a7",
      "instanceId": "i-09dea164a6f2c9d5f",
      "date": "2022-11-30T18:11:00",
      "type": 0
    },
    {
      "recordId": "4c1275ee-3a3f-4e82-8213-e8c6379843da",
      "instanceId": "i-00780850d79c19900",
      "date": "2022-11-30T18:12:00",
      "type": 0
    },
    {
      "recordId": "ab786d83-7572-448c-bdcb-538b49cedf6b",
      "instanceId": "i-09dea164a6f2c9d5f",
      "date": "2022-11-30T18:35:00",
      "type": 0
    },
    {
      "recordId": "ca9102a3-4116-4ba2-b60b-559cec1a006b",
      "instanceId": "i-09dea164a6f2c9d5f",
      "date": "2022-11-30T18:36:00",
      "type": 0
    },
    {
      "recordId": "34cfc47b-0860-405d-b368-60278e903e86",
      "instanceId": "i-00780850d79c19900",
      "date": "2022-11-30T18:37:00",
      "type": 0
    },
    {
      "recordId": "e0857136-f735-4d91-9074-fec5735f9bf6",
      "instanceId": "i-09dea164a6f2c9d5f",
      "date": "2022-11-30T18:38:00",
      "type": 0
    },
    {
      "recordId": "19e92d39-d208-4545-b337-7dc5c9e62193",
      "instanceId": "i-09dea164a6f2c9d5f",
      "date": "2022-11-30T18:39:00",
      "type": 0
    },
    {
      "recordId": "99f18d9a-2845-42fe-8b82-712168406a14",
      "instanceId": "i-09dea164a6f2c9d5f",
      "date": "2022-11-30T18:40:00",
      "type": 0
    },
    {
      "recordId": "d7fe4282-ac92-414a-a1bc-b933a6249d5f",
      "instanceId": "i-09dea164a6f2c9d5f",
      "date": "2022-11-30T18:41:00",
      "type": 0
    },
    {
      "recordId": "b2fae7ba-1866-4c07-95de-ead5312137ed",
      "instanceId": "i-09dea164a6f2c9d5f",
      "date": "2022-12-01T00:38:00",
      "type": 0
    },
    {
      "recordId": "c418c2c6-f6f1-4518-85b0-f68b48a52a36",
      "instanceId": "i-09dea164a6f2c9d5f",
      "date": "2022-12-01T00:39:00",
      "type": 0
    },
    {
      "recordId": "7413fd12-5400-4017-9f92-e9985a0b4d9e",
      "instanceId": "i-09dea164a6f2c9d5f",
      "date": "2022-12-01T00:40:00",
      "type": 0
    },
    {
      "recordId": "daf30698-4d40-40a4-a13a-e7ca22150cea",
      "instanceId": "i-09dea164a6f2c9d5f",
      "date": "2022-12-01T00:41:00",
      "type": 0
    },
    {
      "recordId": "4cc4e1ba-08d8-4c1e-bc01-c86545f85ed7",
      "instanceId": "i-09dea164a6f2c9d5f",
      "date": "2022-12-01T00:42:00",
      "type": 0
    },
    {
      "recordId": "096bdd0d-e3cf-45eb-84dd-8883e578d8c4",
      "instanceId": "i-09dea164a6f2c9d5f",
      "date": "2022-12-01T01:45:00",
      "type": 0
    },
    {
      "recordId": "e412fa3d-8f09-414e-89cc-10f01b469d8c",
      "instanceId": "i-09dea164a6f2c9d5f",
      "date": "2022-12-01T01:46:00",
      "type": 0
    },
    {
      "recordId": "a63db061-b1ef-4b9f-bf50-2bc8616557a0",
      "instanceId": "i-09dea164a6f2c9d5f",
      "date": "2022-12-01T01:47:00",
      "type": 0
    },
    {
      "recordId": "968df61d-acb3-4060-96fc-ce45b57e209a",
      "instanceId": "i-09dea164a6f2c9d5f",
      "date": "2022-12-01T01:48:00",
      "type": 0
    },
    {
      "recordId": "e2823d07-bdb6-46a2-9265-785b5ab0ca1f",
      "instanceId": "i-09dea164a6f2c9d5f",
      "date": "2022-12-01T01:49:00",
      "type": 0
    },
    {
      "recordId": "49378ad2-39f9-45d7-9737-3f5871921314",
      "instanceId": "i-09dea164a6f2c9d5f",
      "date": "2022-12-01T03:09:00",
      "type": 0
    },
    {
      "recordId": "a21d46a3-a2c6-44b6-9ae2-fb3f7208c762",
      "instanceId": "i-09dea164a6f2c9d5f",
      "date": "2022-12-01T03:10:00",
      "type": 0
    },
    {
      "recordId": "154e641e-c5e4-462a-94d8-c5c6149588cc",
      "instanceId": "i-09dea164a6f2c9d5f",
      "date": "2022-12-01T03:11:00",
      "type": 0
    },
    {
      "recordId": "3a67f233-fea2-4686-9c02-ddc74482a4fa",
      "instanceId": "i-09dea164a6f2c9d5f",
      "date": "2022-12-01T03:12:00",
      "type": 0
    },
    {
      "recordId": "dcfe03fc-6534-465f-ad7a-2abcbb24a179",
      "instanceId": "i-09dea164a6f2c9d5f",
      "date": "2022-12-01T03:13:00",
      "type": 0
    },
    {
      "recordId": "5c5b1c98-b0a1-4020-a229-1837da143f26",
      "instanceId": "i-09dea164a6f2c9d5f",
      "date": "2022-12-01T03:14:00",
      "type": 0
    },
    {
      "recordId": "e907735d-3c28-49ed-ac37-6842a3a99300",
      "instanceId": "i-09dea164a6f2c9d5f",
      "date": "2022-12-01T03:15:00",
      "type": 0
    },
    {
      "recordId": "e06012e2-d7ae-4a3c-ad93-1a4216ed987c",
      "instanceId": "i-09dea164a6f2c9d5f",
      "date": "2022-12-01T03:16:00",
      "type": 0
    },
    {
      "recordId": "421d702d-8b0a-4486-9bec-f2e4a4bcfc6f",
      "instanceId": "i-09dea164a6f2c9d5f",
      "date": "2022-12-01T03:17:00",
      "type": 0
    },
    {
      "recordId": "78517f92-063d-47bf-a3ac-25b37156c3e1",
      "instanceId": "i-09dea164a6f2c9d5f",
      "date": "2022-12-01T03:18:00",
      "type": 0
    },
    {
      "recordId": "2faa7b67-1f47-45a9-8996-ada4688845e5",
      "instanceId": "i-09dea164a6f2c9d5f",
      "date": "2022-12-01T03:19:00",
      "type": 0
    },
    {
      "recordId": "7adf23c1-fc4d-4f0d-a6f5-fd87d8531b0e",
      "instanceId": "i-09dea164a6f2c9d5f",
      "date": "2022-12-01T03:20:00",
      "type": 0
    },
    {
      "recordId": "b4af93f1-d782-4426-b648-61d1ea6d56e8",
      "instanceId": "i-09dea164a6f2c9d5f",
      "date": "2022-12-01T03:21:00",
      "type": 0
    },
    {
      "recordId": "9065197b-16f0-455e-9af0-07e02beacec7",
      "instanceId": "i-09dea164a6f2c9d5f",
      "date": "2022-12-01T03:22:00",
      "type": 0
    },
    {
      "recordId": "5fcc27b1-bc12-4898-9b9c-f78668d63f3f",
      "instanceId": "i-09dea164a6f2c9d5f",
      "date": "2022-12-01T03:23:00",
      "type": 0
    },
    {
      "recordId": "e9a33467-bb27-40fc-8621-351d2003d1ec",
      "instanceId": "i-09dea164a6f2c9d5f",
      "date": "2022-12-01T03:24:00",
      "type": 0
    },
    {
      "recordId": "05b85c06-42be-49f2-99fb-de617e5f91d8",
      "instanceId": "i-09dea164a6f2c9d5f",
      "date": "2022-12-01T03:25:00",
      "type": 0
    },
    {
      "recordId": "09340dd6-4da6-468a-9d9f-3974930de909",
      "instanceId": "i-09dea164a6f2c9d5f",
      "date": "2022-12-01T03:26:00",
      "type": 0
    },
    {
      "recordId": "76dbb070-4868-4d68-b5ff-f167cabd549a",
      "instanceId": "i-09dea164a6f2c9d5f",
      "date": "2022-12-01T03:27:00",
      "type": 0
    },
    {
      "recordId": "45360783-7ecd-431b-8ad4-8d41cbabd49d",
      "instanceId": "i-09dea164a6f2c9d5f",
      "date": "2022-12-01T03:28:00",
      "type": 0
    },
    {
      "recordId": "1a825b3c-e2b6-4e41-b184-a24286134843",
      "instanceId": "i-09dea164a6f2c9d5f",
      "date": "2022-12-01T03:29:00",
      "type": 0
    },
    {
      "recordId": "e08fb972-8f66-4fcb-806d-90b796102e8b",
      "instanceId": "i-09dea164a6f2c9d5f",
      "date": "2022-12-01T03:30:00",
      "type": 0
    },
    {
      "recordId": "4baa7b61-e971-4bba-845c-9bcb76fad3f2",
      "instanceId": "i-09dea164a6f2c9d5f",
      "date": "2022-12-01T03:31:00",
      "type": 0
    },
    {
      "recordId": "bb986a2f-26c3-4fec-b1c9-14533829fec9",
      "instanceId": "i-09dea164a6f2c9d5f",
      "date": "2022-12-01T03:32:00",
      "type": 0
    },
    {
      "recordId": "ba4f0ac4-6c88-4ca8-a482-a361735da5f4",
      "instanceId": "i-09dea164a6f2c9d5f",
      "date": "2022-12-01T03:33:00",
      "type": 0
    },
    {
      "recordId": "76e33b14-116e-4897-829c-368145f2cc29",
      "instanceId": "i-09dea164a6f2c9d5f",
      "date": "2022-12-01T03:34:00",
      "type": 0
    },
    {
      "recordId": "2a6e5711-2006-4bc3-9fea-db979ce6d661",
      "instanceId": "i-09dea164a6f2c9d5f",
      "date": "2022-12-01T03:35:00",
      "type": 0
    },
    {
      "recordId": "4df18492-056f-4a8d-a73e-dc45b86a9102",
      "instanceId": "i-09dea164a6f2c9d5f",
      "date": "2022-12-01T03:36:00",
      "type": 0
    },
    {
      "recordId": "d09adacd-dd2c-4635-a259-14e65312b843",
      "instanceId": "i-09dea164a6f2c9d5f",
      "date": "2022-12-01T03:37:00",
      "type": 0
    },
    {
      "recordId": "a8e4f7cc-9e2a-42bf-a8dd-d2ed80b4bff5",
      "instanceId": "i-09dea164a6f2c9d5f",
      "date": "2022-12-01T03:38:00",
      "type": 0
    },
    {
      "recordId": "e51465bb-ddcb-48b7-9677-dc085c2bae86",
      "instanceId": "i-09dea164a6f2c9d5f",
      "date": "2022-12-01T03:39:00",
      "type": 0
    },
    {
      "recordId": "84e2fe78-69c7-4aa5-96a3-8cf5251eabb4",
      "instanceId": "i-09dea164a6f2c9d5f",
      "date": "2022-12-01T03:40:00",
      "type": 0
    },
    {
      "recordId": "97dd6a87-3ede-4faa-81e0-90ed8f2281b6",
      "instanceId": "i-09dea164a6f2c9d5f",
      "date": "2022-12-01T03:41:00",
      "type": 0
    },
    {
      "recordId": "2c1bfdd5-2900-4579-916b-aabfd38f99cc",
      "instanceId": "i-09dea164a6f2c9d5f",
      "date": "2022-12-01T03:42:00",
      "type": 0
    },
    {
      "recordId": "92f16e0a-92a3-40a8-98f8-e303760094a7",
      "instanceId": "i-09dea164a6f2c9d5f",
      "date": "2022-12-01T03:43:00",
      "type": 0
    },
    {
      "recordId": "05e36ba2-b00b-40e5-ad3f-254aac56623b",
      "instanceId": "i-09dea164a6f2c9d5f",
      "date": "2022-12-01T03:44:00",
      "type": 0
    },
    {
      "recordId": "a2c28fc6-1d91-4e4d-a848-49fb050f344b",
      "instanceId": "i-09dea164a6f2c9d5f",
      "date": "2022-12-01T04:07:00",
      "type": 0
    },
    {
      "recordId": "b7611f78-c1b4-49af-8f96-bd15def3bae5",
      "instanceId": "i-09dea164a6f2c9d5f",
      "date": "2022-12-01T04:08:00",
      "type": 0
    },
    {
      "recordId": "9f5185f3-ba59-4f1b-bd8e-016e8dcf5c66",
      "instanceId": "i-09dea164a6f2c9d5f",
      "date": "2022-12-01T04:09:00",
      "type": 0
    },
    {
      "recordId": "dbe9293d-8a83-4582-8923-8e63dc68a639",
      "instanceId": "i-09dea164a6f2c9d5f",
      "date": "2022-12-01T04:10:00",
      "type": 0
    },
    {
      "recordId": "9671f091-91ea-4a3f-854c-578acc398182",
      "instanceId": "i-09dea164a6f2c9d5f",
      "date": "2022-12-01T04:11:00",
      "type": 0
    },
    {
      "recordId": "9eb86584-8002-4d82-bc80-e4c284c42bc6",
      "instanceId": "i-09dea164a6f2c9d5f",
      "date": "2022-12-01T04:12:00",
      "type": 0
    },
    {
      "recordId": "764c2cbd-fdbc-4b5c-8402-de38dd52b660",
      "instanceId": "i-09dea164a6f2c9d5f",
      "date": "2022-12-01T04:13:00",
      "type": 0
    },
    {
      "recordId": "12d033ca-c155-4c5f-950c-75c0292c8fc3",
      "instanceId": "i-09dea164a6f2c9d5f",
      "date": "2022-12-01T04:14:00",
      "type": 0
    },
    {
      "recordId": "b8fdd3fd-3044-4293-bc31-62fb72ea6f90",
      "instanceId": "i-09dea164a6f2c9d5f",
      "date": "2022-12-01T04:15:00",
      "type": 0
    },
    {
      "recordId": "f5a6f936-4d75-4650-890d-67007c9ece52",
      "instanceId": "i-09dea164a6f2c9d5f",
      "date": "2022-12-01T04:16:00",
      "type": 0
    },
    {
      "recordId": "399db814-c196-46aa-a89a-8e08a3b6c678",
      "instanceId": "i-09dea164a6f2c9d5f",
      "date": "2022-12-01T04:17:00",
      "type": 0
    },
    {
      "recordId": "cab8dc19-6a0e-4e47-b364-c973180887e8",
      "instanceId": "i-09dea164a6f2c9d5f",
      "date": "2022-12-01T04:18:00",
      "type": 0
    },
    {
      "recordId": "91ae32b1-63f7-426f-9e9f-6220a1d889a4",
      "instanceId": "i-09dea164a6f2c9d5f",
      "date": "2022-12-02T01:51:00",
      "type": 0
    },
    {
      "recordId": "2053190f-d431-4260-a677-ddb2f2afeae7",
      "instanceId": "i-09dea164a6f2c9d5f",
      "date": "2022-12-02T01:52:00",
      "type": 0
    },
    {
      "recordId": "d633e99e-6fd6-4b92-8cbe-0eac5359da66",
      "instanceId": "i-09dea164a6f2c9d5f",
      "date": "2022-12-02T01:53:00",
      "type": 0
    },
    {
      "recordId": "a1cca22b-ba19-419c-b5d7-2f9af584af51",
      "instanceId": "i-09dea164a6f2c9d5f",
      "date": "2022-12-02T01:54:00",
      "type": 0
    },
    {
      "recordId": "1e526ef8-7450-4f36-ac66-3c6a96793c5d",
      "instanceId": "i-09dea164a6f2c9d5f",
      "date": "2022-12-02T01:55:00",
      "type": 0
    },
    {
      "recordId": "a2d11a03-cfe4-4722-996f-11dcf3598ecf",
      "instanceId": "i-09dea164a6f2c9d5f",
      "date": "2022-12-02T01:56:00",
      "type": 0
    },
    {
      "recordId": "1d8292b9-ffa2-451c-9567-c387b8e98842",
      "instanceId": "i-09dea164a6f2c9d5f",
      "date": "2022-12-02T01:57:00",
      "type": 0
    },
    {
      "recordId": "45e2b79b-faf7-479a-bacc-0f303c085cc2",
      "instanceId": "i-09dea164a6f2c9d5f",
      "date": "2022-12-02T01:58:00",
      "type": 0
    },
    {
      "recordId": "8b08ac6a-acfa-4c4b-9013-ecc3bacfc35b",
      "instanceId": "i-09dea164a6f2c9d5f",
      "date": "2022-12-02T01:59:00",
      "type": 0
    },
    {
      "recordId": "df3bbe04-aef7-4cd0-b295-f072b4e04a42",
      "instanceId": "i-09dea164a6f2c9d5f",
      "date": "2022-12-02T02:00:00",
      "type": 0
    },
    {
      "recordId": "5e13d003-fc47-4b9c-867e-79d9ea509237",
      "instanceId": "i-09dea164a6f2c9d5f",
      "date": "2022-12-02T02:01:00",
      "type": 0
    },
    {
      "recordId": "2f30bb92-b2ad-449d-b73f-e83f70522fdd",
      "instanceId": "i-09dea164a6f2c9d5f",
      "date": "2022-12-02T02:02:00",
      "type": 0
    },
    {
      "recordId": "6497b6b5-a409-45ce-b85b-6e574c1f4485",
      "instanceId": "i-09dea164a6f2c9d5f",
      "date": "2022-12-02T02:03:00",
      "type": 0
    },
    {
      "recordId": "3cf7f31e-0df1-48e2-b207-48e4083a0d05",
      "instanceId": "i-09dea164a6f2c9d5f",
      "date": "2022-12-02T02:04:00",
      "type": 0
    },
    {
      "recordId": "618fd922-b391-48c1-884d-6e9fa585af8c",
      "instanceId": "i-09dea164a6f2c9d5f",
      "date": "2022-12-02T02:05:00",
      "type": 0
    },
    {
      "recordId": "e4bd92ac-ad29-4a3e-8451-1e7c29233e65",
      "instanceId": "i-09dea164a6f2c9d5f",
      "date": "2022-12-02T02:06:00",
      "type": 0
    },
    {
      "recordId": "39d30575-b907-43fe-b14b-8b1769dfbea9",
      "instanceId": "i-09dea164a6f2c9d5f",
      "date": "2022-12-02T02:07:00",
      "type": 0
    },
    {
      "recordId": "7ce7e4c8-80ac-4a89-a829-9725bf5228de",
      "instanceId": "i-09dea164a6f2c9d5f",
      "date": "2022-12-02T02:08:00",
      "type": 0
    },
    {
      "recordId": "9d90558c-579f-42a5-a7c5-a923933d7f3e",
      "instanceId": "i-09dea164a6f2c9d5f",
      "date": "2022-12-04T17:04:00",
      "type": 0
    },
    {
      "recordId": "ef442037-7344-42a7-ad9b-2a16f1bcd288",
      "instanceId": "i-09dea164a6f2c9d5f",
      "date": "2022-12-04T17:05:00",
      "type": 0
    },
    {
      "recordId": "49156764-d51c-4c47-b8b0-28c0af54c554",
      "instanceId": "i-09dea164a6f2c9d5f",
      "date": "2022-12-04T17:06:00",
      "type": 0
    },
    {
      "recordId": "7b0ed8a7-2ff1-4c88-bd15-6fb21592b09f",
      "instanceId": "i-09dea164a6f2c9d5f",
      "date": "2022-12-04T17:07:00",
      "type": 0
    },
    {
      "recordId": "1e03fd21-da25-4b54-8d48-5bf4e11c0a96",
      "instanceId": "i-09dea164a6f2c9d5f",
      "date": "2022-12-04T17:08:00",
      "type": 0
    },
    {
      "recordId": "6f0f2dd9-d8fb-41e6-b5c6-228527c85de6",
      "instanceId": "i-09dea164a6f2c9d5f",
      "date": "2022-12-04T17:09:00",
      "type": 0
    },
    {
      "recordId": "65ab06be-10f0-47cc-9d8f-0cd1bbf5ccbd",
      "instanceId": "i-09dea164a6f2c9d5f",
      "date": "2022-12-04T17:10:00",
      "type": 0
    },
    {
      "recordId": "11ae9b03-81f4-4475-8133-8752bc10dffa",
      "instanceId": "i-09dea164a6f2c9d5f",
      "date": "2022-12-04T23:11:00",
      "type": 0
    },
    {
      "recordId": "5aa30eb9-5c88-42d3-a63e-db2c85a7743f",
      "instanceId": "i-09dea164a6f2c9d5f",
      "date": "2022-12-04T23:12:00",
      "type": 0
    },
    {
      "recordId": "21bdbb5b-3f05-4b2e-9cce-1447794ebd45",
      "instanceId": "i-09dea164a6f2c9d5f",
      "date": "2022-12-04T23:13:00",
      "type": 0
    },
    {
      "recordId": "542c1480-05f0-4b77-b821-dfd574a36e01",
      "instanceId": "i-09dea164a6f2c9d5f",
      "date": "2022-12-04T23:14:00",
      "type": 0
    },
    {
      "recordId": "1ac4839f-8812-422f-a8e3-38b5ce21aa82",
      "instanceId": "i-09dea164a6f2c9d5f",
      "date": "2022-12-04T23:15:00",
      "type": 0
    },
    {
      "recordId": "76ec3743-6664-4e5d-830d-aae24b73f063",
      "instanceId": "i-09dea164a6f2c9d5f",
      "date": "2022-12-04T23:16:00",
      "type": 0
    },
    {
      "recordId": "b9d8b0b5-5a2a-4df5-a7ac-93c4035f1d45",
      "instanceId": "i-09dea164a6f2c9d5f",
      "date": "2022-12-04T23:17:00",
      "type": 0
    },
    {
      "recordId": "80752d75-ce72-485b-ba12-f6cc9725a572",
      "instanceId": "i-09dea164a6f2c9d5f",
      "date": "2022-12-04T23:18:00",
      "type": 0
    },
    {
      "recordId": "3cebfbd7-c451-4011-be97-055b2328eb2b",
      "instanceId": "i-09dea164a6f2c9d5f",
      "date": "2022-12-04T23:19:00",
      "type": 0
    },
    {
      "recordId": "c85a9d26-9fd5-4ab0-a223-4fa66b7e6054",
      "instanceId": "i-09dea164a6f2c9d5f",
      "date": "2022-12-04T23:20:00",
      "type": 0
    },
    {
      "recordId": "3c6f17b1-3f9f-4614-9554-1c1f9b34fb64",
      "instanceId": "i-09dea164a6f2c9d5f",
      "date": "2022-12-04T23:21:00",
      "type": 0
    },
    {
      "recordId": "8b565755-896b-4f9c-9270-0c9c1ddd8220",
      "instanceId": "i-09dea164a6f2c9d5f",
      "date": "2022-12-06T23:02:00",
      "type": 0
    },
    {
      "recordId": "d8acae8d-965d-4aa9-b9c8-10d71a2dd2b4",
      "instanceId": "i-09dea164a6f2c9d5f",
      "date": "2022-12-06T23:03:00",
      "type": 0
    },
    {
      "recordId": "9582740e-6dc0-4f13-a0cc-9c40c6f52e07",
      "instanceId": "i-00780850d79c19900",
      "date": "2022-12-06T23:04:00",
      "type": 0
    },
    {
      "recordId": "1ab63ff2-7240-4d71-be32-dd2899624113",
      "instanceId": "i-09dea164a6f2c9d5f",
      "date": "2022-12-06T23:05:00",
      "type": 0
    },
    {
      "recordId": "4caada2e-19c1-4687-9b00-9997dd65cb82",
      "instanceId": "i-09dea164a6f2c9d5f",
      "date": "2022-12-06T23:06:00",
      "type": 0
    },
    {
      "recordId": "39041e9b-0d57-4b12-a889-f87850805b77",
      "instanceId": "i-09dea164a6f2c9d5f",
      "date": "2022-12-06T23:07:00",
      "type": 0
    },
    {
      "recordId": "7c23dce9-cdce-478c-af14-6510e36188fe",
      "instanceId": "i-09dea164a6f2c9d5f",
      "date": "2022-12-07T23:03:00",
      "type": 0
    },
    {
      "recordId": "14b95a6b-00a2-4cde-ab52-a30e6ea1ae64",
      "instanceId": "i-09dea164a6f2c9d5f",
      "date": "2022-12-07T23:04:00",
      "type": 0
    },
    {
      "recordId": "80898ba0-f3ca-4892-b9ae-4f5831418999",
      "instanceId": "i-09dea164a6f2c9d5f",
      "date": "2022-12-07T23:05:00",
      "type": 0
    },
    {
      "recordId": "78c39cea-0053-4658-9ed3-deef608c6669",
      "instanceId": "i-09dea164a6f2c9d5f",
      "date": "2022-12-07T23:06:00",
      "type": 0
    },
    {
      "recordId": "fcd959c7-0d71-4fb1-84c7-1be4798a057a",
      "instanceId": "i-09dea164a6f2c9d5f",
      "date": "2022-12-07T23:08:00",
      "type": 0
    },
    {
      "recordId": "a3c96edb-2312-421b-9d1d-72a3b63f1a9f",
      "instanceId": "i-09dea164a6f2c9d5f",
      "date": "2022-12-07T23:09:00",
      "type": 0
    },
    {
      "recordId": "7573ac67-55a2-4bce-95b2-9b4de43161ef",
      "instanceId": "i-09dea164a6f2c9d5f",
      "date": "2022-12-07T23:10:00",
      "type": 0
    },
    {
      "recordId": "047445ca-bfcb-4231-b66e-b07092ba0e16",
      "instanceId": "i-09dea164a6f2c9d5f",
      "date": "2022-12-07T23:11:00",
      "type": 0
    },
    {
      "recordId": "7ecc35c0-66db-4a4b-afd7-b4c7e95250ac",
      "instanceId": "i-09dea164a6f2c9d5f",
      "date": "2022-12-07T23:12:00",
      "type": 0
    },
    {
      "recordId": "2b6e1a16-56b3-4c85-a0b0-78435ba2f284",
      "instanceId": "i-09dea164a6f2c9d5f",
      "date": "2022-12-07T23:13:00",
      "type": 0
    },
    {
      "recordId": "2f576229-d032-4d8a-9d11-4252d8a668a1",
      "instanceId": "i-09dea164a6f2c9d5f",
      "date": "2022-12-07T23:14:00",
      "type": 0
    },
    {
      "recordId": "36a6d17d-95e3-425e-953e-8789049fb332",
      "instanceId": "i-09dea164a6f2c9d5f",
      "date": "2022-12-07T23:15:00",
      "type": 0
    },
    {
      "recordId": "9aebf005-8540-47fd-a722-0a4b5e662d33",
      "instanceId": "i-09dea164a6f2c9d5f",
      "date": "2022-12-07T23:16:00",
      "type": 0
    },
    {
      "recordId": "511814dc-4dd1-4c29-82ec-f85a4ecfbf54",
      "instanceId": "i-09dea164a6f2c9d5f",
      "date": "2022-12-07T23:17:00",
      "type": 0
    },
    {
      "recordId": "ceadb25b-431b-43da-825c-19789aa2e3ac",
      "instanceId": "i-09dea164a6f2c9d5f",
      "date": "2022-12-07T23:18:00",
      "type": 0
    },
    {
      "recordId": "fd54b9a5-1372-4703-82b2-509c70af5fbe",
      "instanceId": "i-09dea164a6f2c9d5f",
      "date": "2022-12-07T23:19:00",
      "type": 0
    },
    {
      "recordId": "b5ef9226-3c90-45d7-a7a7-a0dbed6c6d4f",
      "instanceId": "i-09dea164a6f2c9d5f",
      "date": "2022-12-07T23:20:00",
      "type": 0
    },
    {
      "recordId": "f1e70a02-4aa6-4993-82df-886291decb91",
      "instanceId": "i-09dea164a6f2c9d5f",
      "date": "2022-12-07T23:21:00",
      "type": 0
    },
    {
      "recordId": "92bfe678-e969-4da4-af45-d151fd98eb08",
      "instanceId": "i-09dea164a6f2c9d5f",
      "date": "2022-12-07T23:22:00",
      "type": 0
    },
    {
      "recordId": "c9a68e49-3d1b-4013-8e3b-5815e40aad22",
      "instanceId": "i-09dea164a6f2c9d5f",
      "date": "2022-12-08T20:59:00",
      "type": 0
    },
    {
      "recordId": "1b66bf6a-7ab4-4e33-b128-e07b5a33905e",
      "instanceId": "i-09dea164a6f2c9d5f",
      "date": "2022-12-08T21:00:00",
      "type": 0
    },
    {
      "recordId": "4a50d55d-1e3b-4941-90a6-f7ee48d28883",
      "instanceId": "i-09dea164a6f2c9d5f",
      "date": "2022-12-08T21:01:00",
      "type": 0
    },
    {
      "recordId": "c37f4d60-c2cc-4f03-8f50-c35fde7ed6cb",
      "instanceId": "i-09dea164a6f2c9d5f",
      "date": "2022-12-08T21:02:00",
      "type": 0
    },
    {
      "recordId": "0013c598-7772-4d81-9a14-4ed1a422e18b",
      "instanceId": "i-09dea164a6f2c9d5f",
      "date": "2022-12-08T21:03:00",
      "type": 0
    },
    {
      "recordId": "daa42310-2ce3-44d2-8bfc-f43f40467468",
      "instanceId": "i-09dea164a6f2c9d5f",
      "date": "2022-12-08T21:04:00",
      "type": 0
    },
    {
      "recordId": "a46b10bf-2827-4257-be8b-237637bd3312",
      "instanceId": "i-09dea164a6f2c9d5f",
      "date": "2022-12-08T21:05:00",
      "type": 0
    },
    {
      "recordId": "fa38294f-4f1f-45c1-8edd-1e1ec7b90a6c",
      "instanceId": "i-09dea164a6f2c9d5f",
      "date": "2022-12-08T21:06:00",
      "type": 0
    },
    {
      "recordId": "11f2a1be-e270-47a8-bc07-fdbfb01806ee",
      "instanceId": "i-09dea164a6f2c9d5f",
      "date": "2022-12-08T21:07:00",
      "type": 0
    },
    {
      "recordId": "1c13a7fd-f94f-43f8-bcc7-ed3d48737c0f",
      "instanceId": "i-09dea164a6f2c9d5f",
      "date": "2022-12-08T21:08:00",
      "type": 0
    },
    {
      "recordId": "721c0616-74e1-4e56-9aa2-764f66780b13",
      "instanceId": "i-09dea164a6f2c9d5f",
      "date": "2022-12-08T21:09:00",
      "type": 0
    },
    {
      "recordId": "47ad931b-da89-4971-b5ea-65bc2ac13709",
      "instanceId": "i-09dea164a6f2c9d5f",
      "date": "2022-12-08T21:10:00",
      "type": 0
    },
    {
      "recordId": "fdba94b1-779e-4031-acd6-10cee141731f",
      "instanceId": "i-09dea164a6f2c9d5f",
      "date": "2022-12-08T21:11:00",
      "type": 0
    },
    {
      "recordId": "1df6ce9f-252a-4677-8e4b-db0758a808f8",
      "instanceId": "i-09dea164a6f2c9d5f",
      "date": "2022-12-08T21:12:00",
      "type": 0
    }
  ]
}